ask_pepperonit.py
ask_pepperonit-0.0.8.dist-info/LICENSE
ask_pepperonit-0.0.8.dist-info/METADATA
ask_pepperonit-0.0.8.dist-info/WHEEL
ask_pepperonit-0.0.8.dist-info/top_level.txt
ask_pepperonit-0.0.8.dist-info/RECORD
