Metadata-Version: 2.1
Name: ask-pepperonit
Version: 0.0.8
Summary: Say Hello!
Home-page: https://github.com/D7017E/Web_Interaction_Package
Author: Oscar Lundberg
Author-email: jensoscarlundberg95@gmail.com
License: UNKNOWN
Platform: UNKNOWN
Classifier: Programming Language :: Python :: 2.7
Classifier: License :: OSI Approved :: MIT License
Classifier: Operating System :: OS Independent
License-File: LICENSE
Requires-Dist: wikipedia (~=1.4.0)
Requires-Dist: search-google (~=1.2.1)
